django_nyt/__init__.py
django_nyt/admin.py
django_nyt/apps.py
django_nyt/conf.py
django_nyt/consumers.py
django_nyt/decorators.py
django_nyt/forms.py
django_nyt/models.py
django_nyt/routing.py
django_nyt/subscribers.py
django_nyt/urls.py
django_nyt/utils.py
django_nyt/views.py
django_nyt/locale/da/LC_MESSAGES/django.po
django_nyt/locale/de/LC_MESSAGES/django.po
django_nyt/locale/fi/LC_MESSAGES/django.po
django_nyt/locale/ru/LC_MESSAGES/django.po
django_nyt/management/__init__.py
django_nyt/management/commands/__init__.py
django_nyt/management/commands/notifymail.py
django_nyt/migrations/0001_initial.py
django_nyt/migrations/0002_notification_settings.py
django_nyt/migrations/0003_subscription.py
django_nyt/migrations/0004_notification_subscription.py
django_nyt/migrations/0005__v_0_9_2.py
django_nyt/migrations/0006_auto_20141229_1630.py
django_nyt/migrations/0007_add_modified_and_default_settings.py
django_nyt/migrations/0008_auto_20161023_1641.py
django_nyt/migrations/0009_alter_notification_subscription_and_more.py
django_nyt/migrations/0010_settings_created_settings_modified_and_more.py
django_nyt/migrations/__init__.py
django_nyt/templates/notifications/emails/default.txt
django_nyt/templates/notifications/emails/default_subject.txt
django_nyt-1.5.0.dist-info/METADATA
django_nyt-1.5.0.dist-info/WHEEL
django_nyt-1.5.0.dist-info/licenses/LICENSE
django_nyt-1.5.0.dist-info/RECORD
