Metadata-Version: 2.4
Name: django-nyt
Version: 1.5.0
Summary: A pluggable notification system written for the Django framework.
Project-URL: Homepage, https://github.com/django-wiki/django-nyt
Project-URL: Documentation, https://django-nyt.readthedocs.io/en/latest/
Project-URL: Tracker, https://github.com/django-wiki/django-nyt/issues
Project-URL: Source, https://github.com/django-wiki/django-nyt
Project-URL: Funding, https://donate.pypi.org
Project-URL: Release notes, https://github.com/django-wiki/django-nyt/releases
Author-email: Benjamin Bach <benjamin@overtag.dk>
Maintainer-email: Oscar Cortez <om.cortez.2010@gmail.com>
License-Expression: GPL-3.0
License-File: LICENSE
Keywords: alerts,django,notification
Classifier: Development Status :: 5 - Production/Stable
Classifier: Environment :: Web Environment
Classifier: Framework :: Django
Classifier: Intended Audience :: Developers
Classifier: License :: OSI Approved :: GNU General Public License v3 (GPLv3)
Classifier: Operating System :: OS Independent
Classifier: Programming Language :: Python
Classifier: Programming Language :: Python :: 3
Classifier: Programming Language :: Python :: 3 :: Only
Classifier: Programming Language :: Python :: 3.8
Classifier: Programming Language :: Python :: 3.9
Classifier: Programming Language :: Python :: 3.10
Classifier: Programming Language :: Python :: 3.11
Classifier: Topic :: Internet :: WWW/HTTP :: Dynamic Content
Classifier: Topic :: Software Development
Classifier: Topic :: Software Development :: Libraries :: Application Frameworks
Requires-Python: >=3.8
Requires-Dist: django<5.3,>=2.2
Provides-Extra: docs
Requires-Dist: channels==4.0.0; extra == 'docs'
Requires-Dist: sphinx-rtd-theme==1.2.0; extra == 'docs'
Requires-Dist: sphinx==6.2.1; extra == 'docs'
